AUTHORS
CHANGELOG
LICENSE
MANIFEST.in
README.rst
setup.py
Updatorr.egg-info/PKG-INFO
Updatorr.egg-info/SOURCES.txt
Updatorr.egg-info/dependency_links.txt
Updatorr.egg-info/entry_points.txt
Updatorr.egg-info/not-zip-safe
Updatorr.egg-info/requires.txt
Updatorr.egg-info/top_level.txt
updatorr/__init__.py
updatorr/core.py
updatorr/gtkui.py
updatorr/handler_base.py
updatorr/utils.py
updatorr/webui.py
updatorr/data/config.glade
updatorr/data/updatorr.js
updatorr/tracker_handlers/__init__.py
updatorr/tracker_handlers/__init__.pyc
updatorr/tracker_handlers/handler_anidub.py
updatorr/tracker_handlers/handler_rutor.py
updatorr/tracker_handlers/handler_rutracker.py
updatorr/tracker_handlers/handler_rutracker.pyc