Metadata-Version: 1.1
Name: Updatorr
Version: 0.1.8
Summary: Deluge plugin for automatic torrents updates
Home-page: http://github.com/idlesign/deluge-updatorr
Author: Igor 'idle sign' Starikov
Author-email: idlesign@yandex.ru
License: BSD License
Platform: UNKNOWN
Classifier: Development Status :: 4 - Beta
Classifier: Environment :: Plugins
Classifier: Intended Audience :: End Users/Desktop
Classifier: License :: OSI Approved :: BSD License
Classifier: Operating System :: OS Independent
Classifier: Programming Language :: Python
